{"options":{"check_for_updates":true,"comment":null,"compat_foreach":false,"compat_metadata":false,"compat_powerful_this":null,"compat_wrappedjsobject":false,"compatopts_for_requires":true,"noframes":null,"override":{"merge_connects":true,"merge_excludes":true,"merge_includes":true,"merge_matches":true,"orig_connects":["*.redgifs.com","*.gfycat.com","*.gifdeliverynetwork.com","*.cdn.embedly.com"],"orig_excludes":[],"orig_includes":[],"orig_matches":["*://*.gifdeliverynetwork.com/*","*://cdn.embedly.com/widgets/media.html?src=*://*.gfycat.com/*","*://cdn.embedly.com/widgets/media.html?src=*://*.redgifs.com/*","*://*.gfycat.com/*","*://*.redgifs.com/*"],"orig_noframes":null,"orig_run_at":"document-idle","use_blockers":[],"use_connects":[],"use_excludes":[],"use_includes":[],"use_matches":[]},"run_at":null,"sandbox":null,"tab_types":null,"unwrap":null},"settings":{"enabled":true,"position":136},"meta":{"name":"Gfycat AutoHD","uuid":"6d4213e2-33fd-40cb-a277-5165971c01f9","modified":1654575819752,"file_url":"https://greasyfork.org/scripts/388733/code/script.user.js"}}